{
  "image_name": "20260624_160739.jpg.jpeg",
  "manual_homography_plane_points": [],
  "manual_damage_polygons": [
    {
      "damage_id": "manual_1",
      "damage_class": "damage",
      "points": [
        [
          2465,
          1540
        ],
        [
          2359,
          2688
        ],
        [
          3687,
          2746
        ],
        [
          3793,
          1540
        ]
      ]
    }
  ],
  "annotation_source": "main_pipeline_1_hitl_window",
  "hitl_status": "corrected"
}